pybtool/__init__.py
pybtool/host/__init__.py
pybtool/host/att.py
pybtool/host/gatt.py
pybtool/host/hci.py
pybtool/host/hci_interface/__init__.py
pybtool/host/hci_interface/hci.py
pybtool/host/hci_interface/uart.py
pybtool/host/hci_interface/usb.py
pybtool/host/l2cap.py
pybtool/host/rfcomm.py
pybtool/host/sdp.py
pybtool/host/sm.py
pybtool/main.py
pybtool-0.1.0.dist-info/entry_points.txt
pybtool-0.1.0.dist-info/METADATA
pybtool-0.1.0.dist-info/WHEEL
pybtool-0.1.0.dist-info/RECORD
